{"kind":"symbol","schemaVersion":{"minor":3,"patch":0,"major":0},"hierarchy":{"paths":[["doc:\/\/org.cocoapods.SocialRadio\/documentation\/SocialRadio"]]},"sections":[],"topicSections":[{"identifiers":["doc:\/\/org.cocoapods.SocialRadio\/documentation\/SocialRadio\/AutomixIQStatus\/init()"],"anchor":"Initializers","generated":true,"title":"Initializers"},{"identifiers":["doc:\/\/org.cocoapods.SocialRadio\/documentation\/SocialRadio\/AutomixIQStatus\/canBack","doc:\/\/org.cocoapods.SocialRadio\/documentation\/SocialRadio\/AutomixIQStatus\/canMixNow","doc:\/\/org.cocoapods.SocialRadio\/documentation\/SocialRadio\/AutomixIQStatus\/canOnOff","doc:\/\/org.cocoapods.SocialRadio\/documentation\/SocialRadio\/AutomixIQStatus\/canPlayPause","doc:\/\/org.cocoapods.SocialRadio\/documentation\/SocialRadio\/AutomixIQStatus\/canReorderTracks","doc:\/\/org.cocoapods.SocialRadio\/documentation\/SocialRadio\/AutomixIQStatus\/canSeek","doc:\/\/org.cocoapods.SocialRadio\/documentation\/SocialRadio\/AutomixIQStatus\/canSkipToNext","doc:\/\/org.cocoapods.SocialRadio\/documentation\/SocialRadio\/AutomixIQStatus\/canSkipToPrevious","doc:\/\/org.cocoapods.SocialRadio\/documentation\/SocialRadio\/AutomixIQStatus\/explicitLyricsFiltering","doc:\/\/org.cocoapods.SocialRadio\/documentation\/SocialRadio\/AutomixIQStatus\/failedTrackLoadIdentifiers","doc:\/\/org.cocoapods.SocialRadio\/documentation\/SocialRadio\/AutomixIQStatus\/mixId","doc:\/\/org.cocoapods.SocialRadio\/documentation\/SocialRadio\/AutomixIQStatus\/mixing","doc:\/\/org.cocoapods.SocialRadio\/documentation\/SocialRadio\/AutomixIQStatus\/muted","doc:\/\/org.cocoapods.SocialRadio\/documentation\/SocialRadio\/AutomixIQStatus\/nextTransitionDuration","doc:\/\/org.cocoapods.SocialRadio\/documentation\/SocialRadio\/AutomixIQStatus\/normalisedVolume","doc:\/\/org.cocoapods.SocialRadio\/documentation\/SocialRadio\/AutomixIQStatus\/playSpeed","doc:\/\/org.cocoapods.SocialRadio\/documentation\/SocialRadio\/AutomixIQStatus\/playbackMode","doc:\/\/org.cocoapods.SocialRadio\/documentation\/SocialRadio\/AutomixIQStatus\/playing","doc:\/\/org.cocoapods.SocialRadio\/documentation\/SocialRadio\/AutomixIQStatus\/playingTrackCurrentTime","doc:\/\/org.cocoapods.SocialRadio\/documentation\/SocialRadio\/AutomixIQStatus\/playingTrackIdentifier","doc:\/\/org.cocoapods.SocialRadio\/documentation\/SocialRadio\/AutomixIQStatus\/playingTrackIndex","doc:\/\/org.cocoapods.SocialRadio\/documentation\/SocialRadio\/AutomixIQStatus\/playingTrackOriginalSessionId","doc:\/\/org.cocoapods.SocialRadio\/documentation\/SocialRadio\/AutomixIQStatus\/playingTrackStreamingProgress","doc:\/\/org.cocoapods.SocialRadio\/documentation\/SocialRadio\/AutomixIQStatus\/playingTrackTotalTime","doc:\/\/org.cocoapods.SocialRadio\/documentation\/SocialRadio\/AutomixIQStatus\/playlist","doc:\/\/org.cocoapods.SocialRadio\/documentation\/SocialRadio\/AutomixIQStatus\/playlistDiff","doc:\/\/org.cocoapods.SocialRadio\/documentation\/SocialRadio\/AutomixIQStatus\/preferredTransitionDurationSeconds","doc:\/\/org.cocoapods.SocialRadio\/documentation\/SocialRadio\/AutomixIQStatus\/readyToPlay","doc:\/\/org.cocoapods.SocialRadio\/documentation\/SocialRadio\/AutomixIQStatus\/replayOn","doc:\/\/org.cocoapods.SocialRadio\/documentation\/SocialRadio\/AutomixIQStatus\/requestedLoopTrackIdentifier","doc:\/\/org.cocoapods.SocialRadio\/documentation\/SocialRadio\/AutomixIQStatus\/requestedPauseTrackIdentifier","doc:\/\/org.cocoapods.SocialRadio\/documentation\/SocialRadio\/AutomixIQStatus\/transitionStartTimeSeconds","doc:\/\/org.cocoapods.SocialRadio\/documentation\/SocialRadio\/AutomixIQStatus\/vinylStartStop"],"anchor":"Instance-Properties","generated":true,"title":"Instance Properties"},{"identifiers":["doc:\/\/org.cocoapods.SocialRadio\/documentation\/SocialRadio\/AutomixIQStatus\/copy(with:)","doc:\/\/org.cocoapods.SocialRadio\/documentation\/SocialRadio\/AutomixIQStatus\/variableValue(_:)"],"anchor":"Instance-Methods","generated":true,"title":"Instance Methods"},{"identifiers":["doc:\/\/org.cocoapods.SocialRadio\/documentation\/SocialRadio\/AutomixIQStatus\/allStatusVariables()","doc:\/\/org.cocoapods.SocialRadio\/documentation\/SocialRadio\/AutomixIQStatus\/automixIQStatusVariableName(_:)"],"anchor":"Type-Methods","generated":true,"title":"Type Methods"}],"variants":[{"traits":[{"interfaceLanguage":"swift"}],"paths":["\/documentation\/socialradio\/automixiqstatus"]},{"traits":[{"interfaceLanguage":"occ"}],"paths":["\/documentation\/socialradio\/automixiqstatus"]}],"abstract":[{"text":"AutomixIQStatus models the State of the AutomixIQ during playback.","type":"text"}],"identifier":{"url":"doc:\/\/org.cocoapods.SocialRadio\/documentation\/SocialRadio\/AutomixIQStatus","interfaceLanguage":"swift"},"seeAlsoSections":[{"identifiers":["doc:\/\/org.cocoapods.SocialRadio\/documentation\/SocialRadio\/AutomixIQ-article","doc:\/\/org.cocoapods.SocialRadio\/documentation\/SocialRadio\/AutomixIQ","doc:\/\/org.cocoapods.SocialRadio\/documentation\/SocialRadio\/AutomixIQObjC","doc:\/\/org.cocoapods.SocialRadio\/documentation\/SocialRadio\/TunedLogLevel","doc:\/\/org.cocoapods.SocialRadio\/documentation\/SocialRadio\/TunedAutomixPlaybackMode","doc:\/\/org.cocoapods.SocialRadio\/documentation\/SocialRadio\/AutomixIQConfig","doc:\/\/org.cocoapods.SocialRadio\/documentation\/SocialRadio\/AutomixIQPlaylistOperation","doc:\/\/org.cocoapods.SocialRadio\/documentation\/SocialRadio\/TunedArtistModel","doc:\/\/org.cocoapods.SocialRadio\/documentation\/SocialRadio\/TunedPluginMetadataModel","doc:\/\/org.cocoapods.SocialRadio\/documentation\/SocialRadio\/TunedTrackModel","doc:\/\/org.cocoapods.SocialRadio\/documentation\/SocialRadio\/TunedAuthenticationResponse","doc:\/\/org.cocoapods.SocialRadio\/documentation\/SocialRadio\/AutomixIQWaveformModel","doc:\/\/org.cocoapods.SocialRadio\/documentation\/SocialRadio\/TunedRestDelegate","doc:\/\/org.cocoapods.SocialRadio\/documentation\/SocialRadio\/AutomixIQStatusObserverDelegate","doc:\/\/org.cocoapods.SocialRadio\/documentation\/SocialRadio\/AutomixIQMusicCacheDelegate","doc:\/\/org.cocoapods.SocialRadio\/documentation\/SocialRadio\/AutomixIQStatusVariable","doc:\/\/org.cocoapods.SocialRadio\/documentation\/SocialRadio\/AutomixIQPlaylistOperationType"],"anchor":"AutomixIQ","generated":true,"title":"AutomixIQ"}],"relationshipsSections":[{"identifiers":["doc:\/\/org.cocoapods.SocialRadio\/objc(cs)NSObject"],"kind":"relationships","type":"inheritsFrom","title":"Inherits From"},{"identifiers":["doc:\/\/org.cocoapods.SocialRadio\/objc(pl)NSCopying","doc:\/\/org.cocoapods.SocialRadio\/objc(pl)NSObject","doc:\/\/org.cocoapods.SocialRadio\/s7CVarArgP","doc:\/\/org.cocoapods.SocialRadio\/s28CustomDebugStringConvertibleP","doc:\/\/org.cocoapods.SocialRadio\/s23CustomStringConvertibleP","doc:\/\/org.cocoapods.SocialRadio\/SQ","doc:\/\/org.cocoapods.SocialRadio\/SH"],"kind":"relationships","type":"conformsTo","title":"Conforms To"}],"primaryContentSections":[{"kind":"declarations","declarations":[{"tokens":[{"kind":"attribute","text":"@objc"},{"kind":"text","text":" "},{"kind":"keyword","text":"class"},{"kind":"text","text":" "},{"kind":"identifier","text":"AutomixIQStatus"}],"languages":["swift"],"platforms":["iOS"]}]}],"metadata":{"title":"AutomixIQStatus","externalID":"c:@M@SocialRadio@objc(cs)AutomixIQStatus","navigatorTitle":[{"text":"AutomixIQStatus","kind":"identifier"}],"symbolKind":"class","fragments":[{"kind":"keyword","text":"class"},{"kind":"text","text":" "},{"kind":"identifier","text":"AutomixIQStatus"}],"roleHeading":"Class","modules":[{"name":"SocialRadio"}],"role":"symbol"},"references":{"doc://org.cocoapods.SocialRadio/SH":{"identifier":"doc:\/\/org.cocoapods.SocialRadio\/SH","type":"unresolvable","title":"Swift.Hashable"},"doc://org.cocoapods.SocialRadio/documentation/SocialRadio/AutomixIQConfig":{"url":"\/documentation\/socialradio\/automixiqconfig","title":"AutomixIQConfig","abstract":[],"role":"symbol","fragments":[{"text":"class","kind":"keyword"},{"text":" ","kind":"text"},{"text":"AutomixIQConfig","kind":"identifier"}],"identifier":"doc:\/\/org.cocoapods.SocialRadio\/documentation\/SocialRadio\/AutomixIQConfig","navigatorTitle":[{"text":"AutomixIQConfig","kind":"identifier"}],"kind":"symbol","type":"topic"},"doc://org.cocoapods.SocialRadio/objc(pl)NSCopying":{"type":"unresolvable","identifier":"doc:\/\/org.cocoapods.SocialRadio\/objc(pl)NSCopying","title":"NSCopying"},"doc://org.cocoapods.SocialRadio/documentation/SocialRadio/AutomixIQStatus/playingTrackOriginalSessionId":{"role":"symbol","kind":"symbol","title":"playingTrackOriginalSessionId","navigatorTitle":[{"text":"playingTrackOriginalSessionId","kind":"identifier"}],"identifier":"doc:\/\/org.cocoapods.SocialRadio\/documentation\/SocialRadio\/AutomixIQStatus\/playingTrackOriginalSessionId","type":"topic","fragments":[{"text":"var","kind":"keyword"},{"text":" ","kind":"text"},{"text":"playingTrackOriginalSessionId","kind":"identifier"},{"text":": ","kind":"text"},{"preciseIdentifier":"s:SS","text":"String","kind":"typeIdentifier"},{"text":"?","kind":"text"}],"abstract":[],"url":"\/documentation\/socialradio\/automixiqstatus\/playingtrackoriginalsessionid"},"doc://org.cocoapods.SocialRadio/documentation/SocialRadio/AutomixIQStatus/playSpeed":{"identifier":"doc:\/\/org.cocoapods.SocialRadio\/documentation\/SocialRadio\/AutomixIQStatus\/playSpeed","navigatorTitle":[{"kind":"identifier","text":"playSpeed"}],"fragments":[{"kind":"keyword","text":"var"},{"kind":"text","text":" "},{"kind":"identifier","text":"playSpeed"},{"kind":"text","text":": Swift"},{"kind":"text","text":"."},{"kind":"typeIdentifier","preciseIdentifier":"s:Sf","text":"Float"}],"url":"\/documentation\/socialradio\/automixiqstatus\/playspeed","role":"symbol","abstract":[{"text":"Represents the Automix SDK play speed as a factor, from 0.5 to 2","type":"text"}],"type":"topic","title":"playSpeed","kind":"symbol"},"doc://org.cocoapods.SocialRadio/documentation/SocialRadio/AutomixIQStatus/automixIQStatusVariableName(_:)":{"fragments":[{"text":"static","kind":"keyword"},{"text":" ","kind":"text"},{"text":"func","kind":"keyword"},{"text":" ","kind":"text"},{"text":"automixIQStatusVariableName","kind":"identifier"},{"text":"(","kind":"text"},{"preciseIdentifier":"c:@M@SocialRadio@E@AutomixIQStatusVariable","text":"AutomixIQStatusVariable","kind":"typeIdentifier"},{"text":") -> ","kind":"text"},{"preciseIdentifier":"s:SS","text":"String","kind":"typeIdentifier"}],"navigatorTitle":[{"text":"automixIQStatusVariableName:","kind":"identifier"}],"identifier":"doc:\/\/org.cocoapods.SocialRadio\/documentation\/SocialRadio\/AutomixIQStatus\/automixIQStatusVariableName(_:)","title":"automixIQStatusVariableName(_:)","kind":"symbol","url":"\/documentation\/socialradio\/automixiqstatus\/automixiqstatusvariablename(_:)","abstract":[],"type":"topic","role":"symbol"},"doc://org.cocoapods.SocialRadio/documentation/SocialRadio/AutomixIQStatus/playingTrackCurrentTime":{"identifier":"doc:\/\/org.cocoapods.SocialRadio\/documentation\/SocialRadio\/AutomixIQStatus\/playingTrackCurrentTime","abstract":[{"text":"Represents the current playback time of the playing track. If seeking, it reports seek landing time until jump is complete. This should be use on the UI.","type":"text"}],"url":"\/documentation\/socialradio\/automixiqstatus\/playingtrackcurrenttime","kind":"symbol","navigatorTitle":[{"kind":"identifier","text":"playingTrackCurrentTime"}],"type":"topic","title":"playingTrackCurrentTime","role":"symbol","fragments":[{"kind":"keyword","text":"var"},{"kind":"text","text":" "},{"kind":"identifier","text":"playingTrackCurrentTime"},{"kind":"text","text":": "},{"kind":"typeIdentifier","preciseIdentifier":"c:@T@NSTimeInterval","text":"TimeInterval"}]},"doc://org.cocoapods.SocialRadio/documentation/SocialRadio/AutomixIQStatus/transitionStartTimeSeconds":{"kind":"symbol","abstract":[{"text":"Represents the track time in seconds in which the next (or current) transition starts","type":"text"}],"type":"topic","role":"symbol","url":"\/documentation\/socialradio\/automixiqstatus\/transitionstarttimeseconds","navigatorTitle":[{"text":"transitionStartTimeSeconds","kind":"identifier"}],"identifier":"doc:\/\/org.cocoapods.SocialRadio\/documentation\/SocialRadio\/AutomixIQStatus\/transitionStartTimeSeconds","fragments":[{"text":"var","kind":"keyword"},{"text":" ","kind":"text"},{"text":"transitionStartTimeSeconds","kind":"identifier"},{"text":": Swift","kind":"text"},{"text":".","kind":"text"},{"preciseIdentifier":"s:Sf","text":"Float","kind":"typeIdentifier"}],"title":"transitionStartTimeSeconds"},"doc://org.cocoapods.SocialRadio/documentation/SocialRadio/AutomixIQStatus/canSkipToPrevious":{"type":"topic","abstract":[{"text":"Represents wether the engine is ready to skip to a previous track.","type":"text"}],"url":"\/documentation\/socialradio\/automixiqstatus\/canskiptoprevious","fragments":[{"kind":"keyword","text":"var"},{"kind":"text","text":" "},{"kind":"identifier","text":"canSkipToPrevious"},{"kind":"text","text":": "},{"kind":"typeIdentifier","preciseIdentifier":"s:Sb","text":"Bool"}],"kind":"symbol","role":"symbol","identifier":"doc:\/\/org.cocoapods.SocialRadio\/documentation\/SocialRadio\/AutomixIQStatus\/canSkipToPrevious","title":"canSkipToPrevious","navigatorTitle":[{"kind":"identifier","text":"canSkipToPrevious"}]},"doc://org.cocoapods.SocialRadio/documentation/SocialRadio/AutomixIQStatus/nextTransitionDuration":{"kind":"symbol","type":"topic","navigatorTitle":[{"text":"nextTransitionDuration","kind":"identifier"}],"title":"nextTransitionDuration","abstract":[{"text":"Represents the duration of the upcoming transition, 0 if no transition available","type":"text"}],"url":"\/documentation\/socialradio\/automixiqstatus\/nexttransitionduration","identifier":"doc:\/\/org.cocoapods.SocialRadio\/documentation\/SocialRadio\/AutomixIQStatus\/nextTransitionDuration","role":"symbol","fragments":[{"text":"var","kind":"keyword"},{"text":" ","kind":"text"},{"text":"nextTransitionDuration","kind":"identifier"},{"text":": Swift","kind":"text"},{"text":".","kind":"text"},{"preciseIdentifier":"s:Sf","text":"Float","kind":"typeIdentifier"}]},"doc://org.cocoapods.SocialRadio/documentation/SocialRadio/AutomixIQStatus/copy(with:)":{"fragments":[{"text":"func","kind":"keyword"},{"text":" ","kind":"text"},{"text":"copy","kind":"identifier"},{"text":"(","kind":"text"},{"text":"with","kind":"externalParam"},{"text":": ","kind":"text"},{"text":"NSZone","preciseIdentifier":"s:10ObjectiveC6NSZoneV","kind":"typeIdentifier"},{"text":"?) -> ","kind":"text"},{"text":"Any","kind":"keyword"}],"identifier":"doc:\/\/org.cocoapods.SocialRadio\/documentation\/SocialRadio\/AutomixIQStatus\/copy(with:)","role":"symbol","type":"topic","title":"copy(with:)","kind":"symbol","navigatorTitle":[{"text":"copyWithZone:","kind":"identifier"}],"url":"\/documentation\/socialradio\/automixiqstatus\/copy(with:)","abstract":[]},"doc://org.cocoapods.SocialRadio/documentation/SocialRadio/AutomixIQ-article":{"role":"article","type":"topic","url":"\/documentation\/socialradio\/automixiq-article","abstract":[{"text":"Availablity of underlying technologies and APIs.","type":"text"}],"kind":"article","identifier":"doc:\/\/org.cocoapods.SocialRadio\/documentation\/SocialRadio\/AutomixIQ-article","title":"AutomixIQ"},"doc://org.cocoapods.SocialRadio/s23CustomStringConvertibleP":{"type":"unresolvable","identifier":"doc:\/\/org.cocoapods.SocialRadio\/s23CustomStringConvertibleP","title":"Swift.CustomStringConvertible"},"doc://org.cocoapods.SocialRadio/documentation/SocialRadio/TunedArtistModel":{"fragments":[{"text":"class","kind":"keyword"},{"text":" ","kind":"text"},{"text":"TunedArtistModel","kind":"identifier"}],"abstract":[{"type":"text","text":"TunedArtistModel models an artist."}],"identifier":"doc:\/\/org.cocoapods.SocialRadio\/documentation\/SocialRadio\/TunedArtistModel","url":"\/documentation\/socialradio\/tunedartistmodel","kind":"symbol","type":"topic","navigatorTitle":[{"text":"TunedArtistModel","kind":"identifier"}],"title":"TunedArtistModel","role":"symbol"},"doc://org.cocoapods.SocialRadio/documentation/SocialRadio/AutomixIQStatus/requestedLoopTrackIdentifier":{"role":"symbol","navigatorTitle":[{"kind":"identifier","text":"requestedLoopTrackIdentifier"}],"url":"\/documentation\/socialradio\/automixiqstatus\/requestedlooptrackidentifier","title":"requestedLoopTrackIdentifier","abstract":[{"type":"text","text":"Represents the track Automix SDK is currently looping, nil if none is looping"}],"fragments":[{"kind":"keyword","text":"var"},{"kind":"text","text":" "},{"kind":"identifier","text":"requestedLoopTrackIdentifier"},{"kind":"text","text":": "},{"kind":"typeIdentifier","text":"String","preciseIdentifier":"s:SS"},{"kind":"text","text":"?"}],"kind":"symbol","identifier":"doc:\/\/org.cocoapods.SocialRadio\/documentation\/SocialRadio\/AutomixIQStatus\/requestedLoopTrackIdentifier","type":"topic"},"doc://org.cocoapods.SocialRadio/documentation/SocialRadio/AutomixIQStatus/readyToPlay":{"kind":"symbol","navigatorTitle":[{"text":"readyToPlay","kind":"identifier"}],"role":"symbol","fragments":[{"text":"var","kind":"keyword"},{"text":" ","kind":"text"},{"text":"readyToPlay","kind":"identifier"},{"text":": ","kind":"text"},{"text":"Bool","kind":"typeIdentifier","preciseIdentifier":"s:Sb"}],"url":"\/documentation\/socialradio\/automixiqstatus\/readytoplay","abstract":[{"text":"Represents wether the mix is readsy to play or currently loading.","type":"text"}],"identifier":"doc:\/\/org.cocoapods.SocialRadio\/documentation\/SocialRadio\/AutomixIQStatus\/readyToPlay","type":"topic","title":"readyToPlay"},"doc://org.cocoapods.SocialRadio/documentation/SocialRadio/AutomixIQStatus/canSeek":{"fragments":[{"text":"var","kind":"keyword"},{"text":" ","kind":"text"},{"text":"canSeek","kind":"identifier"},{"text":": ","kind":"text"},{"preciseIdentifier":"s:Sb","text":"Bool","kind":"typeIdentifier"}],"navigatorTitle":[{"text":"canSeek","kind":"identifier"}],"title":"canSeek","identifier":"doc:\/\/org.cocoapods.SocialRadio\/documentation\/SocialRadio\/AutomixIQStatus\/canSeek","abstract":[{"type":"text","text":"Represents wether the engine is ready to receive a seek command."}],"kind":"symbol","role":"symbol","type":"topic","url":"\/documentation\/socialradio\/automixiqstatus\/canseek"},"doc://org.cocoapods.SocialRadio/s7CVarArgP":{"identifier":"doc:\/\/org.cocoapods.SocialRadio\/s7CVarArgP","type":"unresolvable","title":"Swift.CVarArg"},"doc://org.cocoapods.SocialRadio/documentation/SocialRadio/TunedLogLevel":{"kind":"symbol","role":"symbol","url":"\/documentation\/socialradio\/tunedloglevel","fragments":[{"kind":"keyword","text":"enum"},{"kind":"text","text":" "},{"kind":"identifier","text":"TunedLogLevel"}],"title":"TunedLogLevel","type":"topic","identifier":"doc:\/\/org.cocoapods.SocialRadio\/documentation\/SocialRadio\/TunedLogLevel","navigatorTitle":[{"kind":"identifier","text":"TunedLogLevel"}],"abstract":[{"type":"text","text":"TunedLogLevel is an enum of all the AutomixIQ available log levels"}]},"doc://org.cocoapods.SocialRadio/documentation/SocialRadio/AutomixIQPlaylistOperation":{"url":"\/documentation\/socialradio\/automixiqplaylistoperation","navigatorTitle":[{"text":"AutomixIQPlaylistOperation","kind":"identifier"}],"kind":"symbol","abstract":[{"type":"text","text":"AutomixIQPlaylistOperation models a move, add or remove operation of a track in a playlist."}],"title":"AutomixIQPlaylistOperation","role":"symbol","fragments":[{"text":"class","kind":"keyword"},{"text":" ","kind":"text"},{"text":"AutomixIQPlaylistOperation","kind":"identifier"}],"type":"topic","identifier":"doc:\/\/org.cocoapods.SocialRadio\/documentation\/SocialRadio\/AutomixIQPlaylistOperation"},"doc://org.cocoapods.SocialRadio/documentation/SocialRadio/AutomixIQStatus/playingTrackIndex":{"title":"playingTrackIndex","navigatorTitle":[{"text":"playingTrackIndex","kind":"identifier"}],"identifier":"doc:\/\/org.cocoapods.SocialRadio\/documentation\/SocialRadio\/AutomixIQStatus\/playingTrackIndex","abstract":[{"text":"Represents the position of the currently playing track in the playlist if not mixing, the front track of the two mixed together if mixing. This would be the track a UI needs to show as playing or active.","type":"text"},{"text":" ","type":"text"},{"text":"If seeking, it reports seek landing track index until jump is complete. This should be use on the UI.","type":"text"}],"url":"\/documentation\/socialradio\/automixiqstatus\/playingtrackindex","type":"topic","fragments":[{"text":"var","kind":"keyword"},{"text":" ","kind":"text"},{"text":"playingTrackIndex","kind":"identifier"},{"text":": ","kind":"text"},{"preciseIdentifier":"s:Si","text":"Int","kind":"typeIdentifier"}],"role":"symbol","kind":"symbol"},"doc://org.cocoapods.SocialRadio/documentation/SocialRadio/TunedTrackModel":{"kind":"symbol","role":"symbol","type":"topic","identifier":"doc:\/\/org.cocoapods.SocialRadio\/documentation\/SocialRadio\/TunedTrackModel","title":"TunedTrackModel","fragments":[{"kind":"keyword","text":"class"},{"kind":"text","text":" "},{"kind":"identifier","text":"TunedTrackModel"}],"navigatorTitle":[{"kind":"identifier","text":"TunedTrackModel"}],"url":"\/documentation\/socialradio\/tunedtrackmodel","abstract":[{"type":"text","text":"TunedTrackModel models a track. This metadata is required."}]},"doc://org.cocoapods.SocialRadio/documentation/SocialRadio/AutomixIQStatus/requestedPauseTrackIdentifier":{"abstract":[{"type":"text","text":"Represents the track Automix SDK is currently flagged to be paused at the end, nil if none is"}],"url":"\/documentation\/socialradio\/automixiqstatus\/requestedpausetrackidentifier","identifier":"doc:\/\/org.cocoapods.SocialRadio\/documentation\/SocialRadio\/AutomixIQStatus\/requestedPauseTrackIdentifier","title":"requestedPauseTrackIdentifier","role":"symbol","fragments":[{"kind":"keyword","text":"var"},{"kind":"text","text":" "},{"kind":"identifier","text":"requestedPauseTrackIdentifier"},{"kind":"text","text":": "},{"kind":"typeIdentifier","text":"String","preciseIdentifier":"s:SS"},{"kind":"text","text":"?"}],"kind":"symbol","navigatorTitle":[{"kind":"identifier","text":"requestedPauseTrackIdentifier"}],"type":"topic"},"doc://org.cocoapods.SocialRadio/documentation/SocialRadio/AutomixIQStatus/preferredTransitionDurationSeconds":{"type":"topic","abstract":[{"type":"text","text":"Represents the preferred Automix SDK transition duration, 0 if disabled."}],"fragments":[{"kind":"keyword","text":"var"},{"kind":"text","text":" "},{"kind":"identifier","text":"preferredTransitionDurationSeconds"},{"kind":"text","text":": Swift"},{"kind":"text","text":"."},{"kind":"typeIdentifier","preciseIdentifier":"s:Sf","text":"Float"}],"identifier":"doc:\/\/org.cocoapods.SocialRadio\/documentation\/SocialRadio\/AutomixIQStatus\/preferredTransitionDurationSeconds","navigatorTitle":[{"kind":"identifier","text":"preferredTransitionDurationSeconds"}],"kind":"symbol","role":"symbol","title":"preferredTransitionDurationSeconds","url":"\/documentation\/socialradio\/automixiqstatus\/preferredtransitiondurationseconds"},"doc://org.cocoapods.SocialRadio/documentation/SocialRadio/TunedPluginMetadataModel":{"fragments":[{"text":"class","kind":"keyword"},{"text":" ","kind":"text"},{"text":"TunedPluginMetadataModel","kind":"identifier"}],"url":"\/documentation\/socialradio\/tunedpluginmetadatamodel","navigatorTitle":[{"text":"TunedPluginMetadataModel","kind":"identifier"}],"role":"symbol","identifier":"doc:\/\/org.cocoapods.SocialRadio\/documentation\/SocialRadio\/TunedPluginMetadataModel","title":"TunedPluginMetadataModel","abstract":[{"type":"text","text":"TunedPluginMetadataModel models metadata of a track traditionally obtained by running plugins on it. Key and BPM are recommented for best mixing."},{"type":"text","text":" "},{"type":"text","text":"The Type entry for bpm and key are “key” and “bpm” (case sensitive) respectively, the values need to be formatted as strings, and the key needs to be in OpenKey format."}],"kind":"symbol","type":"topic"},"doc://org.cocoapods.SocialRadio/documentation/SocialRadio/AutomixIQStatus":{"title":"AutomixIQStatus","kind":"symbol","fragments":[{"text":"class","kind":"keyword"},{"text":" ","kind":"text"},{"text":"AutomixIQStatus","kind":"identifier"}],"navigatorTitle":[{"text":"AutomixIQStatus","kind":"identifier"}],"url":"\/documentation\/socialradio\/automixiqstatus","type":"topic","role":"symbol","identifier":"doc:\/\/org.cocoapods.SocialRadio\/documentation\/SocialRadio\/AutomixIQStatus","abstract":[{"type":"text","text":"AutomixIQStatus models the State of the AutomixIQ during playback."}]},"doc://org.cocoapods.SocialRadio/documentation/SocialRadio":{"identifier":"doc:\/\/org.cocoapods.SocialRadio\/documentation\/SocialRadio","abstract":[{"text":"Broadcast your playlist, mix, or voice to the world.","type":"text"}],"title":"SocialRadio","url":"\/documentation\/socialradio","type":"topic","role":"collection","kind":"symbol"},"doc://org.cocoapods.SocialRadio/documentation/SocialRadio/AutomixIQStatus/normalisedVolume":{"type":"topic","identifier":"doc:\/\/org.cocoapods.SocialRadio\/documentation\/SocialRadio\/AutomixIQStatus\/normalisedVolume","role":"symbol","title":"normalisedVolume","kind":"symbol","fragments":[{"kind":"keyword","text":"var"},{"kind":"text","text":" "},{"kind":"identifier","text":"normalisedVolume"},{"kind":"text","text":": Swift"},{"kind":"text","text":"."},{"preciseIdentifier":"s:Sf","kind":"typeIdentifier","text":"Float"}],"url":"\/documentation\/socialradio\/automixiqstatus\/normalisedvolume","navigatorTitle":[{"kind":"identifier","text":"normalisedVolume"}],"abstract":[{"type":"text","text":"Represents the Automix SDK volume from 1 to 0. Note the device’s iOS Volume acts as a master over this one: if iOS’volume is 0, no sound will be put out regardless of this value."}]},"doc://org.cocoapods.SocialRadio/documentation/SocialRadio/AutomixIQStatus/variableValue(_:)":{"title":"variableValue(_:)","url":"\/documentation\/socialradio\/automixiqstatus\/variablevalue(_:)","abstract":[],"type":"topic","fragments":[{"text":"func","kind":"keyword"},{"text":" ","kind":"text"},{"text":"variableValue","kind":"identifier"},{"text":"(","kind":"text"},{"preciseIdentifier":"c:@M@SocialRadio@E@AutomixIQStatusVariable","text":"AutomixIQStatusVariable","kind":"typeIdentifier"},{"text":") -> ","kind":"text"},{"text":"Any","kind":"keyword"}],"kind":"symbol","role":"symbol","identifier":"doc:\/\/org.cocoapods.SocialRadio\/documentation\/SocialRadio\/AutomixIQStatus\/variableValue(_:)","navigatorTitle":[{"text":"variableValue:","kind":"identifier"}]},"doc://org.cocoapods.SocialRadio/documentation/SocialRadio/AutomixIQStatusObserverDelegate":{"identifier":"doc:\/\/org.cocoapods.SocialRadio\/documentation\/SocialRadio\/AutomixIQStatusObserverDelegate","title":"AutomixIQStatusObserverDelegate","kind":"symbol","url":"\/documentation\/socialradio\/automixiqstatusobserverdelegate","fragments":[{"text":"protocol","kind":"keyword"},{"text":" ","kind":"text"},{"text":"AutomixIQStatusObserverDelegate","kind":"identifier"}],"navigatorTitle":[{"text":"AutomixIQStatusObserverDelegate","kind":"identifier"}],"abstract":[{"text":"AutomixIQStatusObserverDelegate protocol defines the methods to be implemented with observing the status of AutomixIQ to reflect it on a UI.","type":"text"}],"type":"topic","role":"symbol"},"doc://org.cocoapods.SocialRadio/documentation/SocialRadio/AutomixIQ":{"identifier":"doc:\/\/org.cocoapods.SocialRadio\/documentation\/SocialRadio\/AutomixIQ","abstract":[{"type":"text","text":"AutomixIQ represents the AutomixIQ SDK and exposes all its functionality. It follows a Singleton pattern."}],"kind":"symbol","type":"topic","fragments":[{"kind":"keyword","text":"class"},{"kind":"text","text":" "},{"kind":"identifier","text":"AutomixIQ"}],"title":"AutomixIQ","navigatorTitle":[{"kind":"identifier","text":"AutomixIQ"}],"role":"symbol","url":"\/documentation\/socialradio\/automixiq"},"doc://org.cocoapods.SocialRadio/documentation/SocialRadio/AutomixIQStatus/replayOn":{"type":"topic","kind":"symbol","navigatorTitle":[{"kind":"identifier","text":"replayOn"}],"identifier":"doc:\/\/org.cocoapods.SocialRadio\/documentation\/SocialRadio\/AutomixIQStatus\/replayOn","url":"\/documentation\/socialradio\/automixiqstatus\/replayon","title":"replayOn","role":"symbol","abstract":[{"type":"text","text":"Represents wether the engine will replay the current playlist when it ends."}],"fragments":[{"kind":"keyword","text":"var"},{"kind":"text","text":" "},{"kind":"identifier","text":"replayOn"},{"kind":"text","text":": "},{"kind":"typeIdentifier","preciseIdentifier":"s:Sb","text":"Bool"}]},"doc://org.cocoapods.SocialRadio/documentation/SocialRadio/AutomixIQStatus/init()":{"url":"\/documentation\/socialradio\/automixiqstatus\/init()","abstract":[],"kind":"symbol","title":"init()","fragments":[{"text":"init","kind":"identifier"},{"text":"()","kind":"text"}],"role":"symbol","navigatorTitle":[{"text":"init","kind":"identifier"}],"type":"topic","identifier":"doc:\/\/org.cocoapods.SocialRadio\/documentation\/SocialRadio\/AutomixIQStatus\/init()"},"doc://org.cocoapods.SocialRadio/documentation/SocialRadio/AutomixIQStatus/playingTrackStreamingProgress":{"title":"playingTrackStreamingProgress","url":"\/documentation\/socialradio\/automixiqstatus\/playingtrackstreamingprogress","role":"symbol","type":"topic","kind":"symbol","abstract":[{"text":"Represents the percentage of downloaded track.","type":"text"}],"navigatorTitle":[{"text":"playingTrackStreamingProgress","kind":"identifier"}],"fragments":[{"text":"var","kind":"keyword"},{"text":" ","kind":"text"},{"text":"playingTrackStreamingProgress","kind":"identifier"},{"text":": Swift","kind":"text"},{"text":".","kind":"text"},{"preciseIdentifier":"s:Sf","text":"Float","kind":"typeIdentifier"}],"identifier":"doc:\/\/org.cocoapods.SocialRadio\/documentation\/SocialRadio\/AutomixIQStatus\/playingTrackStreamingProgress"},"doc://org.cocoapods.SocialRadio/documentation/SocialRadio/AutomixIQStatus/mixing":{"navigatorTitle":[{"kind":"identifier","text":"mixing"}],"type":"topic","kind":"symbol","identifier":"doc:\/\/org.cocoapods.SocialRadio\/documentation\/SocialRadio\/AutomixIQStatus\/mixing","abstract":[{"type":"text","text":"Represents if more than one track is concurrently playing from Automix SDK (mixing), true if it is, false otherwise."}],"url":"\/documentation\/socialradio\/automixiqstatus\/mixing","role":"symbol","fragments":[{"kind":"keyword","text":"var"},{"kind":"text","text":" "},{"kind":"identifier","text":"mixing"},{"kind":"text","text":": "},{"preciseIdentifier":"s:Sb","kind":"typeIdentifier","text":"Bool"}],"title":"mixing"},"doc://org.cocoapods.SocialRadio/documentation/SocialRadio/TunedAutomixPlaybackMode":{"url":"\/documentation\/socialradio\/tunedautomixplaybackmode","title":"TunedAutomixPlaybackMode","type":"topic","role":"symbol","abstract":[{"text":"AutomixIQ playback mode","type":"text"}],"fragments":[{"kind":"keyword","text":"enum"},{"kind":"text","text":" "},{"kind":"identifier","text":"TunedAutomixPlaybackMode"}],"navigatorTitle":[{"kind":"identifier","text":"TunedAutomixPlaybackMode"}],"identifier":"doc:\/\/org.cocoapods.SocialRadio\/documentation\/SocialRadio\/TunedAutomixPlaybackMode","kind":"symbol"},"doc://org.cocoapods.SocialRadio/documentation/SocialRadio/AutomixIQStatus/mixId":{"fragments":[{"text":"var","kind":"keyword"},{"text":" ","kind":"text"},{"text":"mixId","kind":"identifier"},{"text":": ","kind":"text"},{"text":"Int64","kind":"typeIdentifier","preciseIdentifier":"s:s5Int64V"}],"title":"mixId","type":"topic","role":"symbol","abstract":[],"kind":"symbol","identifier":"doc:\/\/org.cocoapods.SocialRadio\/documentation\/SocialRadio\/AutomixIQStatus\/mixId","url":"\/documentation\/socialradio\/automixiqstatus\/mixid","navigatorTitle":[{"text":"mixId","kind":"identifier"}]},"doc://org.cocoapods.SocialRadio/documentation/SocialRadio/AutomixIQMusicCacheDelegate":{"abstract":[{"text":"AutomixIQMusicCacheDelegate protocol defines the methods to be implemented with storing and providing cached track data","type":"text"}],"title":"AutomixIQMusicCacheDelegate","kind":"symbol","type":"topic","url":"\/documentation\/socialradio\/automixiqmusiccachedelegate","identifier":"doc:\/\/org.cocoapods.SocialRadio\/documentation\/SocialRadio\/AutomixIQMusicCacheDelegate","navigatorTitle":[{"text":"AutomixIQMusicCacheDelegate","kind":"identifier"}],"role":"symbol","fragments":[{"text":"protocol","kind":"keyword"},{"text":" ","kind":"text"},{"text":"AutomixIQMusicCacheDelegate","kind":"identifier"}]},"doc://org.cocoapods.SocialRadio/documentation/SocialRadio/AutomixIQStatus/playbackMode":{"abstract":[],"type":"topic","title":"playbackMode","url":"\/documentation\/socialradio\/automixiqstatus\/playbackmode","identifier":"doc:\/\/org.cocoapods.SocialRadio\/documentation\/SocialRadio\/AutomixIQStatus\/playbackMode","navigatorTitle":[{"kind":"identifier","text":"playbackMode"}],"kind":"symbol","fragments":[{"kind":"keyword","text":"var"},{"kind":"text","text":" "},{"kind":"identifier","text":"playbackMode"},{"kind":"text","text":": "},{"kind":"typeIdentifier","text":"Int","preciseIdentifier":"s:Si"}],"role":"symbol"},"doc://org.cocoapods.SocialRadio/documentation/SocialRadio/AutomixIQStatus/canPlayPause":{"identifier":"doc:\/\/org.cocoapods.SocialRadio\/documentation\/SocialRadio\/AutomixIQStatus\/canPlayPause","title":"canPlayPause","kind":"symbol","navigatorTitle":[{"text":"canPlayPause","kind":"identifier"}],"abstract":[{"text":"Represents wether the engine is ready to receive a play or pause command.","type":"text"}],"role":"symbol","url":"\/documentation\/socialradio\/automixiqstatus\/canplaypause","type":"topic","fragments":[{"text":"var","kind":"keyword"},{"text":" ","kind":"text"},{"text":"canPlayPause","kind":"identifier"},{"text":": ","kind":"text"},{"text":"Bool","preciseIdentifier":"s:Sb","kind":"typeIdentifier"}]},"doc://org.cocoapods.SocialRadio/documentation/SocialRadio/AutomixIQStatusVariable":{"type":"topic","url":"\/documentation\/socialradio\/automixiqstatusvariable","role":"symbol","kind":"symbol","navigatorTitle":[{"text":"AutomixIQStatusVariable","kind":"identifier"}],"fragments":[{"text":"enum","kind":"keyword"},{"text":" ","kind":"text"},{"text":"AutomixIQStatusVariable","kind":"identifier"}],"identifier":"doc:\/\/org.cocoapods.SocialRadio\/documentation\/SocialRadio\/AutomixIQStatusVariable","abstract":[{"text":"AutomixIQ status variable type","type":"text"}],"title":"AutomixIQStatusVariable"},"doc://org.cocoapods.SocialRadio/documentation/SocialRadio/TunedAuthenticationResponse":{"identifier":"doc:\/\/org.cocoapods.SocialRadio\/documentation\/SocialRadio\/TunedAuthenticationResponse","type":"topic","kind":"symbol","role":"symbol","title":"TunedAuthenticationResponse","fragments":[{"kind":"keyword","text":"class"},{"kind":"text","text":" "},{"kind":"identifier","text":"TunedAuthenticationResponse"}],"navigatorTitle":[{"kind":"identifier","text":"TunedAuthenticationResponse"}],"url":"\/documentation\/socialradio\/tunedauthenticationresponse","abstract":[{"type":"text","text":"TunedAuthenticationResponse models the response of a Tuned OAuth request"}]},"doc://org.cocoapods.SocialRadio/documentation/SocialRadio/AutomixIQStatus/canMixNow":{"kind":"symbol","type":"topic","fragments":[{"text":"var","kind":"keyword"},{"text":" ","kind":"text"},{"text":"canMixNow","kind":"identifier"},{"text":": ","kind":"text"},{"text":"Bool","kind":"typeIdentifier","preciseIdentifier":"s:Sb"}],"role":"symbol","navigatorTitle":[{"text":"canMixNow","kind":"identifier"}],"identifier":"doc:\/\/org.cocoapods.SocialRadio\/documentation\/SocialRadio\/AutomixIQStatus\/canMixNow","url":"\/documentation\/socialradio\/automixiqstatus\/canmixnow","title":"canMixNow","abstract":[{"text":"Represents wether the ‘next’ action would lead to a proper mix or a regular jumps. Depends on wether we had enough time to analyze the next track or not.","type":"text"}]},"doc://org.cocoapods.SocialRadio/documentation/SocialRadio/AutomixIQStatus/allStatusVariables()":{"url":"\/documentation\/socialradio\/automixiqstatus\/allstatusvariables()","kind":"symbol","role":"symbol","type":"topic","identifier":"doc:\/\/org.cocoapods.SocialRadio\/documentation\/SocialRadio\/AutomixIQStatus\/allStatusVariables()","navigatorTitle":[{"kind":"identifier","text":"allStatusVariables"}],"abstract":[],"fragments":[{"text":"static","kind":"keyword"},{"text":" ","kind":"text"},{"text":"func","kind":"keyword"},{"text":" ","kind":"text"},{"text":"allStatusVariables","kind":"identifier"},{"text":"() -> [","kind":"text"},{"text":"NSNumber","kind":"typeIdentifier","preciseIdentifier":"c:objc(cs)NSNumber"},{"kind":"text","text":"]"}],"title":"allStatusVariables()"},"doc://org.cocoapods.SocialRadio/documentation/SocialRadio/AutomixIQStatus/canBack":{"identifier":"doc:\/\/org.cocoapods.SocialRadio\/documentation\/SocialRadio\/AutomixIQStatus\/canBack","title":"canBack","fragments":[{"kind":"keyword","text":"var"},{"kind":"text","text":" "},{"kind":"identifier","text":"canBack"},{"kind":"text","text":": "},{"kind":"typeIdentifier","preciseIdentifier":"s:Sb","text":"Bool"}],"navigatorTitle":[{"kind":"identifier","text":"canBack"}],"url":"\/documentation\/socialradio\/automixiqstatus\/canback","type":"topic","abstract":[{"type":"text","text":"Represents wether the engine is ready to skip to the beginning of the current track."}],"kind":"symbol","role":"symbol"},"doc://org.cocoapods.SocialRadio/SQ":{"identifier":"doc:\/\/org.cocoapods.SocialRadio\/SQ","type":"unresolvable","title":"Swift.Equatable"},"doc://org.cocoapods.SocialRadio/documentation/SocialRadio/AutomixIQStatus/playlistDiff":{"fragments":[{"kind":"keyword","text":"var"},{"kind":"text","text":" "},{"kind":"identifier","text":"playlistDiff"},{"kind":"text","text":": ["},{"kind":"typeIdentifier","preciseIdentifier":"s:SS","text":"String"},{"kind":"text","text":" : ["},{"kind":"typeIdentifier","preciseIdentifier":"c:@M@SocialRadio@objc(cs)AutomixIQPlaylistOperation","text":"AutomixIQPlaylistOperation"},{"kind":"text","text":"]]?"}],"navigatorTitle":[{"kind":"identifier","text":"playlistDiff"}],"abstract":[],"identifier":"doc:\/\/org.cocoapods.SocialRadio\/documentation\/SocialRadio\/AutomixIQStatus\/playlistDiff","role":"symbol","kind":"symbol","type":"topic","url":"\/documentation\/socialradio\/automixiqstatus\/playlistdiff","title":"playlistDiff"},"doc://org.cocoapods.SocialRadio/documentation/SocialRadio/AutomixIQStatus/playlist":{"abstract":[{"text":"Represents the list of track identifiers in the order they will be played","type":"text"}],"navigatorTitle":[{"text":"playlist","kind":"identifier"}],"type":"topic","url":"\/documentation\/socialradio\/automixiqstatus\/playlist","fragments":[{"text":"var","kind":"keyword"},{"text":" ","kind":"text"},{"text":"playlist","kind":"identifier"},{"text":": [","kind":"text"},{"preciseIdentifier":"s:SS","text":"String","kind":"typeIdentifier"},{"text":"]","kind":"text"}],"role":"symbol","kind":"symbol","title":"playlist","identifier":"doc:\/\/org.cocoapods.SocialRadio\/documentation\/SocialRadio\/AutomixIQStatus\/playlist"},"doc://org.cocoapods.SocialRadio/documentation/SocialRadio/AutomixIQStatus/playingTrackIdentifier":{"url":"\/documentation\/socialradio\/automixiqstatus\/playingtrackidentifier","role":"symbol","title":"playingTrackIdentifier","type":"topic","abstract":[{"type":"text","text":"Represents the identifier of the currently playing track if not mixing, the front track of the two mixed together if mixing. This would be the track a UI needs to show as playing or active."}],"fragments":[{"kind":"keyword","text":"var"},{"kind":"text","text":" "},{"kind":"identifier","text":"playingTrackIdentifier"},{"kind":"text","text":": "},{"kind":"typeIdentifier","text":"String","preciseIdentifier":"s:SS"},{"kind":"text","text":"?"}],"navigatorTitle":[{"kind":"identifier","text":"playingTrackIdentifier"}],"identifier":"doc:\/\/org.cocoapods.SocialRadio\/documentation\/SocialRadio\/AutomixIQStatus\/playingTrackIdentifier","kind":"symbol"},"doc://org.cocoapods.SocialRadio/documentation/SocialRadio/AutomixIQPlaylistOperationType":{"url":"\/documentation\/socialradio\/automixiqplaylistoperationtype","abstract":[],"identifier":"doc:\/\/org.cocoapods.SocialRadio\/documentation\/SocialRadio\/AutomixIQPlaylistOperationType","kind":"symbol","fragments":[{"kind":"keyword","text":"enum"},{"kind":"text","text":" "},{"kind":"identifier","text":"AutomixIQPlaylistOperationType"}],"navigatorTitle":[{"kind":"identifier","text":"AutomixIQPlaylistOperationType"}],"title":"AutomixIQPlaylistOperationType","type":"topic","role":"symbol"},"doc://org.cocoapods.SocialRadio/objc(pl)NSObject":{"title":"ObjectiveC.NSObjectProtocol","type":"unresolvable","identifier":"doc:\/\/org.cocoapods.SocialRadio\/objc(pl)NSObject"},"doc://org.cocoapods.SocialRadio/documentation/SocialRadio/AutomixIQStatus/muted":{"title":"muted","identifier":"doc:\/\/org.cocoapods.SocialRadio\/documentation\/SocialRadio\/AutomixIQStatus\/muted","fragments":[{"kind":"keyword","text":"var"},{"kind":"text","text":" "},{"kind":"identifier","text":"muted"},{"kind":"text","text":": "},{"kind":"typeIdentifier","preciseIdentifier":"s:Sb","text":"Bool"}],"navigatorTitle":[{"kind":"identifier","text":"muted"}],"type":"topic","role":"symbol","url":"\/documentation\/socialradio\/automixiqstatus\/muted","kind":"symbol","abstract":[{"type":"text","text":"Represents whether Automix SDK is muted or not. True if muted, false otherwise."}]},"doc://org.cocoapods.SocialRadio/s28CustomDebugStringConvertibleP":{"title":"Swift.CustomDebugStringConvertible","type":"unresolvable","identifier":"doc:\/\/org.cocoapods.SocialRadio\/s28CustomDebugStringConvertibleP"},"doc://org.cocoapods.SocialRadio/documentation/SocialRadio/AutomixIQStatus/vinylStartStop":{"navigatorTitle":[{"kind":"identifier","text":"vinylStartStop"}],"type":"topic","abstract":[{"type":"text","text":"Represents wether the engine does the vinyl sound effects when play\/pause"}],"fragments":[{"kind":"keyword","text":"var"},{"kind":"text","text":" "},{"kind":"identifier","text":"vinylStartStop"},{"kind":"text","text":": "},{"kind":"typeIdentifier","preciseIdentifier":"s:Sb","text":"Bool"}],"url":"\/documentation\/socialradio\/automixiqstatus\/vinylstartstop","title":"vinylStartStop","identifier":"doc:\/\/org.cocoapods.SocialRadio\/documentation\/SocialRadio\/AutomixIQStatus\/vinylStartStop","role":"symbol","kind":"symbol"},"doc://org.cocoapods.SocialRadio/documentation/SocialRadio/AutomixIQStatus/canSkipToNext":{"url":"\/documentation\/socialradio\/automixiqstatus\/canskiptonext","kind":"symbol","abstract":[{"type":"text","text":"Represents wether the engine is ready to skip to the next track. If playing the last track of the playlist and “repeat” is off, this will be false."}],"identifier":"doc:\/\/org.cocoapods.SocialRadio\/documentation\/SocialRadio\/AutomixIQStatus\/canSkipToNext","fragments":[{"text":"var","kind":"keyword"},{"text":" ","kind":"text"},{"text":"canSkipToNext","kind":"identifier"},{"text":": ","kind":"text"},{"preciseIdentifier":"s:Sb","text":"Bool","kind":"typeIdentifier"}],"title":"canSkipToNext","type":"topic","role":"symbol","navigatorTitle":[{"text":"canSkipToNext","kind":"identifier"}]},"doc://org.cocoapods.SocialRadio/documentation/SocialRadio/AutomixIQStatus/canOnOff":{"identifier":"doc:\/\/org.cocoapods.SocialRadio\/documentation\/SocialRadio\/AutomixIQStatus\/canOnOff","type":"topic","url":"\/documentation\/socialradio\/automixiqstatus\/canonoff","abstract":[{"type":"text","text":"Represents if the SDK can be turned On or off. It is true if not other On \/ Off action is ongoing, flase otherwise. When this switch is true, On \/Off actions return an error."}],"kind":"symbol","navigatorTitle":[{"kind":"identifier","text":"canOnOff"}],"role":"symbol","fragments":[{"kind":"keyword","text":"var"},{"kind":"text","text":" "},{"kind":"identifier","text":"canOnOff"},{"kind":"text","text":": "},{"kind":"typeIdentifier","preciseIdentifier":"s:Sb","text":"Bool"}],"title":"canOnOff"},"doc://org.cocoapods.SocialRadio/documentation/SocialRadio/AutomixIQStatus/playingTrackTotalTime":{"navigatorTitle":[{"text":"playingTrackTotalTime","kind":"identifier"}],"role":"symbol","kind":"symbol","identifier":"doc:\/\/org.cocoapods.SocialRadio\/documentation\/SocialRadio\/AutomixIQStatus\/playingTrackTotalTime","title":"playingTrackTotalTime","url":"\/documentation\/socialradio\/automixiqstatus\/playingtracktotaltime","abstract":[{"type":"text","text":"Represents the total playback time of the playing track."}],"type":"topic","fragments":[{"text":"var","kind":"keyword"},{"text":" ","kind":"text"},{"text":"playingTrackTotalTime","kind":"identifier"},{"text":": ","kind":"text"},{"preciseIdentifier":"c:@T@NSTimeInterval","text":"TimeInterval","kind":"typeIdentifier"}]},"doc://org.cocoapods.SocialRadio/documentation/SocialRadio/AutomixIQStatus/canReorderTracks":{"navigatorTitle":[{"kind":"identifier","text":"canReorderTracks"}],"title":"canReorderTracks","url":"\/documentation\/socialradio\/automixiqstatus\/canreordertracks","identifier":"doc:\/\/org.cocoapods.SocialRadio\/documentation\/SocialRadio\/AutomixIQStatus\/canReorderTracks","fragments":[{"kind":"keyword","text":"var"},{"kind":"text","text":" "},{"kind":"identifier","text":"canReorderTracks"},{"kind":"text","text":": "},{"kind":"typeIdentifier","preciseIdentifier":"s:Sb","text":"Bool"}],"abstract":[{"type":"text","text":"Represents wether the engine is ready to receive a reorder tracks command."}],"role":"symbol","kind":"symbol","type":"topic"},"doc://org.cocoapods.SocialRadio/documentation/SocialRadio/AutomixIQObjC":{"type":"topic","fragments":[{"text":"class","kind":"keyword"},{"text":" ","kind":"text"},{"text":"AutomixIQObjC","kind":"identifier"}],"identifier":"doc:\/\/org.cocoapods.SocialRadio\/documentation\/SocialRadio\/AutomixIQObjC","abstract":[],"title":"AutomixIQObjC","kind":"symbol","url":"\/documentation\/socialradio\/automixiqobjc","role":"symbol","navigatorTitle":[{"text":"AutomixIQObjC","kind":"identifier"}]},"doc://org.cocoapods.SocialRadio/documentation/SocialRadio/AutomixIQStatus/failedTrackLoadIdentifiers":{"type":"topic","kind":"symbol","title":"failedTrackLoadIdentifiers","identifier":"doc:\/\/org.cocoapods.SocialRadio\/documentation\/SocialRadio\/AutomixIQStatus\/failedTrackLoadIdentifiers","navigatorTitle":[{"text":"failedTrackLoadIdentifiers","kind":"identifier"}],"fragments":[{"text":"var","kind":"keyword"},{"text":" ","kind":"text"},{"text":"failedTrackLoadIdentifiers","kind":"identifier"},{"text":": [","kind":"text"},{"preciseIdentifier":"s:SS","text":"String","kind":"typeIdentifier"},{"text":"]?","kind":"text"}],"abstract":[{"type":"text","text":"Represents the tracks that failed loading for any reason"}],"url":"\/documentation\/socialradio\/automixiqstatus\/failedtrackloadidentifiers","role":"symbol"},"doc://org.cocoapods.SocialRadio/documentation/SocialRadio/AutomixIQStatus/playing":{"navigatorTitle":[{"kind":"identifier","text":"playing"}],"url":"\/documentation\/socialradio\/automixiqstatus\/playing","type":"topic","title":"playing","fragments":[{"kind":"keyword","text":"var"},{"kind":"text","text":" "},{"kind":"identifier","text":"playing"},{"kind":"text","text":": "},{"kind":"typeIdentifier","preciseIdentifier":"s:Sb","text":"Bool"}],"identifier":"doc:\/\/org.cocoapods.SocialRadio\/documentation\/SocialRadio\/AutomixIQStatus\/playing","kind":"symbol","role":"symbol","abstract":[{"type":"text","text":"Represents if sound is playing from Automix SDK, true if it is, false otherwise."}]},"doc://org.cocoapods.SocialRadio/objc(cs)NSObject":{"title":"NSObject","type":"unresolvable","identifier":"doc:\/\/org.cocoapods.SocialRadio\/objc(cs)NSObject"},"doc://org.cocoapods.SocialRadio/documentation/SocialRadio/TunedRestDelegate":{"identifier":"doc:\/\/org.cocoapods.SocialRadio\/documentation\/SocialRadio\/TunedRestDelegate","abstract":[{"text":"TunedRestDelegate protocol defines the methods to be implemented that will provide AutomixIQ the credentials and identifiers to Tuned Global’s backend","type":"text"}],"type":"topic","kind":"symbol","url":"\/documentation\/socialradio\/tunedrestdelegate","navigatorTitle":[{"text":"TunedRestDelegate","kind":"identifier"}],"title":"TunedRestDelegate","fragments":[{"kind":"keyword","text":"protocol"},{"text":" ","kind":"text"},{"text":"TunedRestDelegate","kind":"identifier"}],"role":"symbol"},"doc://org.cocoapods.SocialRadio/documentation/SocialRadio/AutomixIQWaveformModel":{"url":"\/documentation\/socialradio\/automixiqwaveformmodel","fragments":[{"kind":"keyword","text":"class"},{"kind":"text","text":" "},{"kind":"identifier","text":"AutomixIQWaveformModel"}],"navigatorTitle":[{"kind":"identifier","text":"AutomixIQWaveformModel"}],"kind":"symbol","identifier":"doc:\/\/org.cocoapods.SocialRadio\/documentation\/SocialRadio\/AutomixIQWaveformModel","title":"AutomixIQWaveformModel","abstract":[{"type":"text","text":"AutomixIQWaveformModel models the waveform of a track."}],"type":"topic","role":"symbol"},"doc://org.cocoapods.SocialRadio/documentation/SocialRadio/AutomixIQStatus/explicitLyricsFiltering":{"navigatorTitle":[{"kind":"identifier","text":"explicitLyricsFiltering"}],"abstract":[],"kind":"symbol","url":"\/documentation\/socialradio\/automixiqstatus\/explicitlyricsfiltering","fragments":[{"kind":"keyword","text":"var"},{"kind":"text","text":" "},{"kind":"identifier","text":"explicitLyricsFiltering"},{"kind":"text","text":": "},{"kind":"typeIdentifier","preciseIdentifier":"s:Sb","text":"Bool"}],"type":"topic","identifier":"doc:\/\/org.cocoapods.SocialRadio\/documentation\/SocialRadio\/AutomixIQStatus\/explicitLyricsFiltering","title":"explicitLyricsFiltering","role":"symbol"}},"variantOverrides":[{"patch":[{"value":"occ","path":"\/identifier\/interfaceLanguage","op":"replace"},{"value":"Class","path":"\/metadata\/roleHeading","op":"replace"},{"value":"AutomixIQStatus","path":"\/metadata\/title","op":"replace"},{"value":"class","path":"\/metadata\/symbolKind","op":"replace"},{"value":[{"text":"AutomixIQStatus","kind":"identifier"}],"path":"\/metadata\/fragments","op":"replace"},{"op":"replace","path":"\/metadata\/navigatorTitle","value":[{"kind":"identifier","text":"AutomixIQStatus"}]},{"op":"replace","path":"\/topicSections","value":[{"anchor":"Instance-Properties","identifiers":["doc:\/\/org.cocoapods.SocialRadio\/documentation\/SocialRadio\/AutomixIQStatus\/canBack","doc:\/\/org.cocoapods.SocialRadio\/documentation\/SocialRadio\/AutomixIQStatus\/canMixNow","doc:\/\/org.cocoapods.SocialRadio\/documentation\/SocialRadio\/AutomixIQStatus\/canOnOff","doc:\/\/org.cocoapods.SocialRadio\/documentation\/SocialRadio\/AutomixIQStatus\/canPlayPause","doc:\/\/org.cocoapods.SocialRadio\/documentation\/SocialRadio\/AutomixIQStatus\/canReorderTracks","doc:\/\/org.cocoapods.SocialRadio\/documentation\/SocialRadio\/AutomixIQStatus\/canSeek","doc:\/\/org.cocoapods.SocialRadio\/documentation\/SocialRadio\/AutomixIQStatus\/canSkipToNext","doc:\/\/org.cocoapods.SocialRadio\/documentation\/SocialRadio\/AutomixIQStatus\/canSkipToPrevious","doc:\/\/org.cocoapods.SocialRadio\/documentation\/SocialRadio\/AutomixIQStatus\/explicitLyricsFiltering","doc:\/\/org.cocoapods.SocialRadio\/documentation\/SocialRadio\/AutomixIQStatus\/failedTrackLoadIdentifiers","doc:\/\/org.cocoapods.SocialRadio\/documentation\/SocialRadio\/AutomixIQStatus\/mixId","doc:\/\/org.cocoapods.SocialRadio\/documentation\/SocialRadio\/AutomixIQStatus\/mixing","doc:\/\/org.cocoapods.SocialRadio\/documentation\/SocialRadio\/AutomixIQStatus\/muted","doc:\/\/org.cocoapods.SocialRadio\/documentation\/SocialRadio\/AutomixIQStatus\/nextTransitionDuration","doc:\/\/org.cocoapods.SocialRadio\/documentation\/SocialRadio\/AutomixIQStatus\/normalisedVolume","doc:\/\/org.cocoapods.SocialRadio\/documentation\/SocialRadio\/AutomixIQStatus\/playSpeed","doc:\/\/org.cocoapods.SocialRadio\/documentation\/SocialRadio\/AutomixIQStatus\/playbackMode","doc:\/\/org.cocoapods.SocialRadio\/documentation\/SocialRadio\/AutomixIQStatus\/playing","doc:\/\/org.cocoapods.SocialRadio\/documentation\/SocialRadio\/AutomixIQStatus\/playingTrackCurrentTime","doc:\/\/org.cocoapods.SocialRadio\/documentation\/SocialRadio\/AutomixIQStatus\/playingTrackIdentifier","doc:\/\/org.cocoapods.SocialRadio\/documentation\/SocialRadio\/AutomixIQStatus\/playingTrackIndex","doc:\/\/org.cocoapods.SocialRadio\/documentation\/SocialRadio\/AutomixIQStatus\/playingTrackOriginalSessionId","doc:\/\/org.cocoapods.SocialRadio\/documentation\/SocialRadio\/AutomixIQStatus\/playingTrackStreamingProgress","doc:\/\/org.cocoapods.SocialRadio\/documentation\/SocialRadio\/AutomixIQStatus\/playingTrackTotalTime","doc:\/\/org.cocoapods.SocialRadio\/documentation\/SocialRadio\/AutomixIQStatus\/playlist","doc:\/\/org.cocoapods.SocialRadio\/documentation\/SocialRadio\/AutomixIQStatus\/playlistDiff","doc:\/\/org.cocoapods.SocialRadio\/documentation\/SocialRadio\/AutomixIQStatus\/preferredTransitionDurationSeconds","doc:\/\/org.cocoapods.SocialRadio\/documentation\/SocialRadio\/AutomixIQStatus\/readyToPlay","doc:\/\/org.cocoapods.SocialRadio\/documentation\/SocialRadio\/AutomixIQStatus\/replayOn","doc:\/\/org.cocoapods.SocialRadio\/documentation\/SocialRadio\/AutomixIQStatus\/requestedLoopTrackIdentifier","doc:\/\/org.cocoapods.SocialRadio\/documentation\/SocialRadio\/AutomixIQStatus\/requestedPauseTrackIdentifier","doc:\/\/org.cocoapods.SocialRadio\/documentation\/SocialRadio\/AutomixIQStatus\/transitionStartTimeSeconds","doc:\/\/org.cocoapods.SocialRadio\/documentation\/SocialRadio\/AutomixIQStatus\/vinylStartStop"],"generated":true,"title":"Instance Properties"},{"anchor":"Instance-Methods","identifiers":["doc:\/\/org.cocoapods.SocialRadio\/documentation\/SocialRadio\/AutomixIQStatus\/copy(with:)","doc:\/\/org.cocoapods.SocialRadio\/documentation\/SocialRadio\/AutomixIQStatus\/init()","doc:\/\/org.cocoapods.SocialRadio\/documentation\/SocialRadio\/AutomixIQStatus\/variableValue(_:)"],"generated":true,"title":"Instance Methods"},{"anchor":"Type-Methods","identifiers":["doc:\/\/org.cocoapods.SocialRadio\/documentation\/SocialRadio\/AutomixIQStatus\/allStatusVariables()","doc:\/\/org.cocoapods.SocialRadio\/documentation\/SocialRadio\/AutomixIQStatus\/automixIQStatusVariableName(_:)"],"generated":true,"title":"Type Methods"}]},{"op":"replace","path":"\/relationshipsSections","value":[{"title":"Inherits From","kind":"relationships","type":"inheritsFrom","identifiers":["doc:\/\/org.cocoapods.SocialRadio\/objc(cs)NSObject"]},{"title":"Conforms To","kind":"relationships","type":"conformsTo","identifiers":["doc:\/\/org.cocoapods.SocialRadio\/objc(pl)NSCopying"]}]},{"op":"replace","path":"\/seeAlsoSections","value":[{"identifiers":["doc:\/\/org.cocoapods.SocialRadio\/documentation\/SocialRadio\/AutomixIQ-article","doc:\/\/org.cocoapods.SocialRadio\/documentation\/SocialRadio\/AutomixIQ","doc:\/\/org.cocoapods.SocialRadio\/documentation\/SocialRadio\/TunedLogLevel","doc:\/\/org.cocoapods.SocialRadio\/documentation\/SocialRadio\/TunedAutomixPlaybackMode","doc:\/\/org.cocoapods.SocialRadio\/documentation\/SocialRadio\/AutomixIQConfig","doc:\/\/org.cocoapods.SocialRadio\/documentation\/SocialRadio\/AutomixIQPlaylistOperation","doc:\/\/org.cocoapods.SocialRadio\/documentation\/SocialRadio\/TunedArtistModel","doc:\/\/org.cocoapods.SocialRadio\/documentation\/SocialRadio\/TunedPluginMetadataModel","doc:\/\/org.cocoapods.SocialRadio\/documentation\/SocialRadio\/TunedTrackModel","doc:\/\/org.cocoapods.SocialRadio\/documentation\/SocialRadio\/TunedAuthenticationResponse","doc:\/\/org.cocoapods.SocialRadio\/documentation\/SocialRadio\/AutomixIQWaveformModel","doc:\/\/org.cocoapods.SocialRadio\/documentation\/SocialRadio\/TunedRestDelegate","doc:\/\/org.cocoapods.SocialRadio\/documentation\/SocialRadio\/AutomixIQStatusObserverDelegate","doc:\/\/org.cocoapods.SocialRadio\/documentation\/SocialRadio\/AutomixIQMusicCacheDelegate","doc:\/\/org.cocoapods.SocialRadio\/documentation\/SocialRadio\/AutomixIQStatusVariable","doc:\/\/org.cocoapods.SocialRadio\/documentation\/SocialRadio\/AutomixIQPlaylistOperationType"],"generated":true,"anchor":"AutomixIQ","title":"AutomixIQ"}]},{"op":"replace","path":"\/primaryContentSections\/0","value":{"declarations":[{"platforms":["iOS"],"tokens":[{"text":"@interface","kind":"keyword"},{"text":" ","kind":"text"},{"text":"AutomixIQStatus","kind":"identifier"},{"text":" : ","kind":"text"},{"preciseIdentifier":"c:objc(cs)NSObject","text":"NSObject","kind":"typeIdentifier"}],"languages":["occ"]}],"kind":"declarations"}},{"op":"replace","path":"\/references\/doc:~1~1org.cocoapods.SocialRadio~1documentation~1SocialRadio~1AutomixIQConfig\/title","value":"AutomixIQConfig"},{"path":"\/references\/doc:~1~1org.cocoapods.SocialRadio~1documentation~1SocialRadio~1AutomixIQConfig\/fragments","op":"replace","value":[{"kind":"identifier","text":"AutomixIQConfig"}]},{"path":"\/references\/doc:~1~1org.cocoapods.SocialRadio~1documentation~1SocialRadio~1AutomixIQConfig\/navigatorTitle","op":"replace","value":[{"kind":"identifier","text":"AutomixIQConfig"}]},{"path":"\/references\/doc:~1~1org.cocoapods.SocialRadio~1documentation~1SocialRadio~1AutomixIQStatus~1playingTrackOriginalSessionId\/title","op":"replace","value":"playingTrackOriginalSessionId"},{"path":"\/references\/doc:~1~1org.cocoapods.SocialRadio~1documentation~1SocialRadio~1AutomixIQStatus~1playingTrackOriginalSessionId\/fragments","op":"replace","value":[{"text":"playingTrackOriginalSessionId","kind":"identifier"}]},{"path":"\/references\/doc:~1~1org.cocoapods.SocialRadio~1documentation~1SocialRadio~1AutomixIQStatus~1playSpeed\/title","op":"replace","value":"playSpeed"},{"path":"\/references\/doc:~1~1org.cocoapods.SocialRadio~1documentation~1SocialRadio~1AutomixIQStatus~1playSpeed\/fragments","op":"replace","value":[{"text":"playSpeed","kind":"identifier"}]},{"path":"\/references\/doc:~1~1org.cocoapods.SocialRadio~1documentation~1SocialRadio~1AutomixIQStatus~1automixIQStatusVariableName(_:)\/title","op":"replace","value":"automixIQStatusVariableName:"},{"path":"\/references\/doc:~1~1org.cocoapods.SocialRadio~1documentation~1SocialRadio~1AutomixIQStatus~1automixIQStatusVariableName(_:)\/fragments","op":"replace","value":[{"kind":"text","text":"+ "},{"kind":"identifier","text":"automixIQStatusVariableName:"}]},{"path":"\/references\/doc:~1~1org.cocoapods.SocialRadio~1documentation~1SocialRadio~1AutomixIQStatus~1playingTrackCurrentTime\/title","op":"replace","value":"playingTrackCurrentTime"},{"path":"\/references\/doc:~1~1org.cocoapods.SocialRadio~1documentation~1SocialRadio~1AutomixIQStatus~1playingTrackCurrentTime\/fragments","op":"replace","value":[{"kind":"identifier","text":"playingTrackCurrentTime"}]},{"path":"\/references\/doc:~1~1org.cocoapods.SocialRadio~1documentation~1SocialRadio~1AutomixIQStatus~1transitionStartTimeSeconds\/title","op":"replace","value":"transitionStartTimeSeconds"},{"path":"\/references\/doc:~1~1org.cocoapods.SocialRadio~1documentation~1SocialRadio~1AutomixIQStatus~1transitionStartTimeSeconds\/fragments","op":"replace","value":[{"kind":"identifier","text":"transitionStartTimeSeconds"}]},{"path":"\/references\/doc:~1~1org.cocoapods.SocialRadio~1documentation~1SocialRadio~1AutomixIQStatus~1canSkipToPrevious\/title","op":"replace","value":"canSkipToPrevious"},{"path":"\/references\/doc:~1~1org.cocoapods.SocialRadio~1documentation~1SocialRadio~1AutomixIQStatus~1canSkipToPrevious\/fragments","op":"replace","value":[{"kind":"identifier","text":"canSkipToPrevious"}]},{"path":"\/references\/doc:~1~1org.cocoapods.SocialRadio~1documentation~1SocialRadio~1AutomixIQStatus~1nextTransitionDuration\/title","op":"replace","value":"nextTransitionDuration"},{"path":"\/references\/doc:~1~1org.cocoapods.SocialRadio~1documentation~1SocialRadio~1AutomixIQStatus~1nextTransitionDuration\/fragments","op":"replace","value":[{"text":"nextTransitionDuration","kind":"identifier"}]},{"path":"\/references\/doc:~1~1org.cocoapods.SocialRadio~1documentation~1SocialRadio~1AutomixIQStatus~1copy(with:)\/title","op":"replace","value":"copyWithZone:"},{"path":"\/references\/doc:~1~1org.cocoapods.SocialRadio~1documentation~1SocialRadio~1AutomixIQStatus~1copy(with:)\/fragments","op":"replace","value":[{"text":"- ","kind":"text"},{"text":"copyWithZone:","kind":"identifier"}]},{"path":"\/references\/doc:~1~1org.cocoapods.SocialRadio~1documentation~1SocialRadio~1TunedArtistModel\/title","op":"replace","value":"TunedArtistModel"},{"path":"\/references\/doc:~1~1org.cocoapods.SocialRadio~1documentation~1SocialRadio~1TunedArtistModel\/fragments","op":"replace","value":[{"text":"TunedArtistModel","kind":"identifier"}]},{"path":"\/references\/doc:~1~1org.cocoapods.SocialRadio~1documentation~1SocialRadio~1TunedArtistModel\/navigatorTitle","op":"replace","value":[{"text":"TunedArtistModel","kind":"identifier"}]},{"path":"\/references\/doc:~1~1org.cocoapods.SocialRadio~1documentation~1SocialRadio~1AutomixIQStatus~1requestedLoopTrackIdentifier\/title","op":"replace","value":"requestedLoopTrackIdentifier"},{"path":"\/references\/doc:~1~1org.cocoapods.SocialRadio~1documentation~1SocialRadio~1AutomixIQStatus~1requestedLoopTrackIdentifier\/fragments","op":"replace","value":[{"text":"requestedLoopTrackIdentifier","kind":"identifier"}]},{"path":"\/references\/doc:~1~1org.cocoapods.SocialRadio~1documentation~1SocialRadio~1AutomixIQStatus~1readyToPlay\/title","op":"replace","value":"readyToPlay"},{"path":"\/references\/doc:~1~1org.cocoapods.SocialRadio~1documentation~1SocialRadio~1AutomixIQStatus~1readyToPlay\/fragments","op":"replace","value":[{"text":"readyToPlay","kind":"identifier"}]},{"path":"\/references\/doc:~1~1org.cocoapods.SocialRadio~1documentation~1SocialRadio~1AutomixIQStatus~1canSeek\/title","op":"replace","value":"canSeek"},{"path":"\/references\/doc:~1~1org.cocoapods.SocialRadio~1documentation~1SocialRadio~1AutomixIQStatus~1canSeek\/fragments","op":"replace","value":[{"text":"canSeek","kind":"identifier"}]},{"path":"\/references\/doc:~1~1org.cocoapods.SocialRadio~1documentation~1SocialRadio~1TunedLogLevel\/title","op":"replace","value":"TunedLogLevel"},{"path":"\/references\/doc:~1~1org.cocoapods.SocialRadio~1documentation~1SocialRadio~1TunedLogLevel\/fragments","op":"replace","value":[{"text":"TunedLogLevel","kind":"identifier"}]},{"path":"\/references\/doc:~1~1org.cocoapods.SocialRadio~1documentation~1SocialRadio~1TunedLogLevel\/navigatorTitle","op":"replace","value":[{"kind":"identifier","text":"TunedLogLevel"}]},{"path":"\/references\/doc:~1~1org.cocoapods.SocialRadio~1documentation~1SocialRadio~1AutomixIQPlaylistOperation\/title","op":"replace","value":"AutomixIQPlaylistOperation"},{"path":"\/references\/doc:~1~1org.cocoapods.SocialRadio~1documentation~1SocialRadio~1AutomixIQPlaylistOperation\/fragments","op":"replace","value":[{"kind":"identifier","text":"AutomixIQPlaylistOperation"}]},{"path":"\/references\/doc:~1~1org.cocoapods.SocialRadio~1documentation~1SocialRadio~1AutomixIQPlaylistOperation\/navigatorTitle","op":"replace","value":[{"kind":"identifier","text":"AutomixIQPlaylistOperation"}]},{"path":"\/references\/doc:~1~1org.cocoapods.SocialRadio~1documentation~1SocialRadio~1AutomixIQStatus~1playingTrackIndex\/title","op":"replace","value":"playingTrackIndex"},{"path":"\/references\/doc:~1~1org.cocoapods.SocialRadio~1documentation~1SocialRadio~1AutomixIQStatus~1playingTrackIndex\/fragments","op":"replace","value":[{"text":"playingTrackIndex","kind":"identifier"}]},{"path":"\/references\/doc:~1~1org.cocoapods.SocialRadio~1documentation~1SocialRadio~1TunedTrackModel\/title","op":"replace","value":"TunedTrackModel"},{"path":"\/references\/doc:~1~1org.cocoapods.SocialRadio~1documentation~1SocialRadio~1TunedTrackModel\/fragments","op":"replace","value":[{"text":"TunedTrackModel","kind":"identifier"}]},{"path":"\/references\/doc:~1~1org.cocoapods.SocialRadio~1documentation~1SocialRadio~1TunedTrackModel\/navigatorTitle","op":"replace","value":[{"kind":"identifier","text":"TunedTrackModel"}]},{"path":"\/references\/doc:~1~1org.cocoapods.SocialRadio~1documentation~1SocialRadio~1AutomixIQStatus~1requestedPauseTrackIdentifier\/title","op":"replace","value":"requestedPauseTrackIdentifier"},{"path":"\/references\/doc:~1~1org.cocoapods.SocialRadio~1documentation~1SocialRadio~1AutomixIQStatus~1requestedPauseTrackIdentifier\/fragments","op":"replace","value":[{"kind":"identifier","text":"requestedPauseTrackIdentifier"}]},{"path":"\/references\/doc:~1~1org.cocoapods.SocialRadio~1documentation~1SocialRadio~1AutomixIQStatus~1preferredTransitionDurationSeconds\/title","op":"replace","value":"preferredTransitionDurationSeconds"},{"path":"\/references\/doc:~1~1org.cocoapods.SocialRadio~1documentation~1SocialRadio~1AutomixIQStatus~1preferredTransitionDurationSeconds\/fragments","op":"replace","value":[{"kind":"identifier","text":"preferredTransitionDurationSeconds"}]},{"path":"\/references\/doc:~1~1org.cocoapods.SocialRadio~1documentation~1SocialRadio~1TunedPluginMetadataModel\/title","op":"replace","value":"TunedPluginMetadataModel"},{"path":"\/references\/doc:~1~1org.cocoapods.SocialRadio~1documentation~1SocialRadio~1TunedPluginMetadataModel\/fragments","op":"replace","value":[{"text":"TunedPluginMetadataModel","kind":"identifier"}]},{"path":"\/references\/doc:~1~1org.cocoapods.SocialRadio~1documentation~1SocialRadio~1TunedPluginMetadataModel\/navigatorTitle","op":"replace","value":[{"kind":"identifier","text":"TunedPluginMetadataModel"}]},{"path":"\/references\/doc:~1~1org.cocoapods.SocialRadio~1documentation~1SocialRadio~1AutomixIQStatus\/title","op":"replace","value":"AutomixIQStatus"},{"path":"\/references\/doc:~1~1org.cocoapods.SocialRadio~1documentation~1SocialRadio~1AutomixIQStatus\/fragments","op":"replace","value":[{"kind":"identifier","text":"AutomixIQStatus"}]},{"path":"\/references\/doc:~1~1org.cocoapods.SocialRadio~1documentation~1SocialRadio~1AutomixIQStatus\/navigatorTitle","op":"replace","value":[{"text":"AutomixIQStatus","kind":"identifier"}]},{"path":"\/references\/doc:~1~1org.cocoapods.SocialRadio~1documentation~1SocialRadio~1AutomixIQStatus~1normalisedVolume\/title","op":"replace","value":"normalisedVolume"},{"path":"\/references\/doc:~1~1org.cocoapods.SocialRadio~1documentation~1SocialRadio~1AutomixIQStatus~1normalisedVolume\/fragments","op":"replace","value":[{"text":"normalisedVolume","kind":"identifier"}]},{"path":"\/references\/doc:~1~1org.cocoapods.SocialRadio~1documentation~1SocialRadio~1AutomixIQStatus~1variableValue(_:)\/title","op":"replace","value":"variableValue:"},{"path":"\/references\/doc:~1~1org.cocoapods.SocialRadio~1documentation~1SocialRadio~1AutomixIQStatus~1variableValue(_:)\/fragments","op":"replace","value":[{"text":"- ","kind":"text"},{"text":"variableValue:","kind":"identifier"}]},{"path":"\/references\/doc:~1~1org.cocoapods.SocialRadio~1documentation~1SocialRadio~1AutomixIQStatusObserverDelegate\/title","op":"replace","value":"AutomixIQStatusObserverDelegate"},{"path":"\/references\/doc:~1~1org.cocoapods.SocialRadio~1documentation~1SocialRadio~1AutomixIQStatusObserverDelegate\/fragments","op":"replace","value":[{"text":"AutomixIQStatusObserverDelegate","kind":"identifier"}]},{"path":"\/references\/doc:~1~1org.cocoapods.SocialRadio~1documentation~1SocialRadio~1AutomixIQStatusObserverDelegate\/navigatorTitle","op":"replace","value":[{"text":"AutomixIQStatusObserverDelegate","kind":"identifier"}]},{"path":"\/references\/doc:~1~1org.cocoapods.SocialRadio~1documentation~1SocialRadio~1AutomixIQ\/title","op":"replace","value":"AutomixIQ"},{"path":"\/references\/doc:~1~1org.cocoapods.SocialRadio~1documentation~1SocialRadio~1AutomixIQ\/fragments","op":"replace","value":[{"text":"AutomixIQ","kind":"identifier"}]},{"path":"\/references\/doc:~1~1org.cocoapods.SocialRadio~1documentation~1SocialRadio~1AutomixIQ\/navigatorTitle","op":"replace","value":[{"text":"AutomixIQ","kind":"identifier"}]},{"path":"\/references\/doc:~1~1org.cocoapods.SocialRadio~1documentation~1SocialRadio~1AutomixIQStatus~1replayOn\/title","op":"replace","value":"replayOn"},{"path":"\/references\/doc:~1~1org.cocoapods.SocialRadio~1documentation~1SocialRadio~1AutomixIQStatus~1replayOn\/fragments","op":"replace","value":[{"text":"replayOn","kind":"identifier"}]},{"path":"\/references\/doc:~1~1org.cocoapods.SocialRadio~1documentation~1SocialRadio~1AutomixIQStatus~1init()\/title","op":"replace","value":"init"},{"path":"\/references\/doc:~1~1org.cocoapods.SocialRadio~1documentation~1SocialRadio~1AutomixIQStatus~1init()\/fragments","op":"replace","value":[{"text":"- ","kind":"text"},{"text":"init","kind":"identifier"}]},{"path":"\/references\/doc:~1~1org.cocoapods.SocialRadio~1documentation~1SocialRadio~1AutomixIQStatus~1playingTrackStreamingProgress\/title","op":"replace","value":"playingTrackStreamingProgress"},{"path":"\/references\/doc:~1~1org.cocoapods.SocialRadio~1documentation~1SocialRadio~1AutomixIQStatus~1playingTrackStreamingProgress\/fragments","op":"replace","value":[{"kind":"identifier","text":"playingTrackStreamingProgress"}]},{"path":"\/references\/doc:~1~1org.cocoapods.SocialRadio~1documentation~1SocialRadio~1AutomixIQStatus~1mixing\/title","op":"replace","value":"mixing"},{"path":"\/references\/doc:~1~1org.cocoapods.SocialRadio~1documentation~1SocialRadio~1AutomixIQStatus~1mixing\/fragments","op":"replace","value":[{"text":"mixing","kind":"identifier"}]},{"path":"\/references\/doc:~1~1org.cocoapods.SocialRadio~1documentation~1SocialRadio~1TunedAutomixPlaybackMode\/title","op":"replace","value":"TunedAutomixPlaybackMode"},{"path":"\/references\/doc:~1~1org.cocoapods.SocialRadio~1documentation~1SocialRadio~1TunedAutomixPlaybackMode\/fragments","op":"replace","value":[{"text":"TunedAutomixPlaybackMode","kind":"identifier"}]},{"path":"\/references\/doc:~1~1org.cocoapods.SocialRadio~1documentation~1SocialRadio~1TunedAutomixPlaybackMode\/navigatorTitle","op":"replace","value":[{"text":"TunedAutomixPlaybackMode","kind":"identifier"}]},{"path":"\/references\/doc:~1~1org.cocoapods.SocialRadio~1documentation~1SocialRadio~1AutomixIQStatus~1mixId\/title","op":"replace","value":"mixId"},{"path":"\/references\/doc:~1~1org.cocoapods.SocialRadio~1documentation~1SocialRadio~1AutomixIQStatus~1mixId\/fragments","op":"replace","value":[{"text":"mixId","kind":"identifier"}]},{"path":"\/references\/doc:~1~1org.cocoapods.SocialRadio~1documentation~1SocialRadio~1AutomixIQMusicCacheDelegate\/title","op":"replace","value":"AutomixIQMusicCacheDelegate"},{"path":"\/references\/doc:~1~1org.cocoapods.SocialRadio~1documentation~1SocialRadio~1AutomixIQMusicCacheDelegate\/fragments","op":"replace","value":[{"kind":"identifier","text":"AutomixIQMusicCacheDelegate"}]},{"path":"\/references\/doc:~1~1org.cocoapods.SocialRadio~1documentation~1SocialRadio~1AutomixIQMusicCacheDelegate\/navigatorTitle","op":"replace","value":[{"text":"AutomixIQMusicCacheDelegate","kind":"identifier"}]},{"path":"\/references\/doc:~1~1org.cocoapods.SocialRadio~1documentation~1SocialRadio~1AutomixIQStatus~1playbackMode\/title","op":"replace","value":"playbackMode"},{"path":"\/references\/doc:~1~1org.cocoapods.SocialRadio~1documentation~1SocialRadio~1AutomixIQStatus~1playbackMode\/fragments","op":"replace","value":[{"text":"playbackMode","kind":"identifier"}]},{"path":"\/references\/doc:~1~1org.cocoapods.SocialRadio~1documentation~1SocialRadio~1AutomixIQStatus~1canPlayPause\/title","op":"replace","value":"canPlayPause"},{"path":"\/references\/doc:~1~1org.cocoapods.SocialRadio~1documentation~1SocialRadio~1AutomixIQStatus~1canPlayPause\/fragments","op":"replace","value":[{"text":"canPlayPause","kind":"identifier"}]},{"path":"\/references\/doc:~1~1org.cocoapods.SocialRadio~1documentation~1SocialRadio~1AutomixIQStatusVariable\/title","op":"replace","value":"AutomixIQStatusVariable"},{"path":"\/references\/doc:~1~1org.cocoapods.SocialRadio~1documentation~1SocialRadio~1AutomixIQStatusVariable\/fragments","op":"replace","value":[{"text":"AutomixIQStatusVariable","kind":"identifier"}]},{"path":"\/references\/doc:~1~1org.cocoapods.SocialRadio~1documentation~1SocialRadio~1AutomixIQStatusVariable\/navigatorTitle","op":"replace","value":[{"kind":"identifier","text":"AutomixIQStatusVariable"}]},{"path":"\/references\/doc:~1~1org.cocoapods.SocialRadio~1documentation~1SocialRadio~1TunedAuthenticationResponse\/title","op":"replace","value":"TunedAuthenticationResponse"},{"path":"\/references\/doc:~1~1org.cocoapods.SocialRadio~1documentation~1SocialRadio~1TunedAuthenticationResponse\/fragments","op":"replace","value":[{"kind":"identifier","text":"TunedAuthenticationResponse"}]},{"path":"\/references\/doc:~1~1org.cocoapods.SocialRadio~1documentation~1SocialRadio~1TunedAuthenticationResponse\/navigatorTitle","op":"replace","value":[{"text":"TunedAuthenticationResponse","kind":"identifier"}]},{"path":"\/references\/doc:~1~1org.cocoapods.SocialRadio~1documentation~1SocialRadio~1AutomixIQStatus~1canMixNow\/title","op":"replace","value":"canMixNow"},{"path":"\/references\/doc:~1~1org.cocoapods.SocialRadio~1documentation~1SocialRadio~1AutomixIQStatus~1canMixNow\/fragments","op":"replace","value":[{"text":"canMixNow","kind":"identifier"}]},{"path":"\/references\/doc:~1~1org.cocoapods.SocialRadio~1documentation~1SocialRadio~1AutomixIQStatus~1allStatusVariables()\/title","op":"replace","value":"allStatusVariables"},{"path":"\/references\/doc:~1~1org.cocoapods.SocialRadio~1documentation~1SocialRadio~1AutomixIQStatus~1allStatusVariables()\/fragments","op":"replace","value":[{"text":"+ ","kind":"text"},{"text":"allStatusVariables","kind":"identifier"}]},{"path":"\/references\/doc:~1~1org.cocoapods.SocialRadio~1documentation~1SocialRadio~1AutomixIQStatus~1canBack\/title","op":"replace","value":"canBack"},{"path":"\/references\/doc:~1~1org.cocoapods.SocialRadio~1documentation~1SocialRadio~1AutomixIQStatus~1canBack\/fragments","op":"replace","value":[{"text":"canBack","kind":"identifier"}]},{"path":"\/references\/doc:~1~1org.cocoapods.SocialRadio~1documentation~1SocialRadio~1AutomixIQStatus~1playlistDiff\/title","op":"replace","value":"playlistDiff"},{"path":"\/references\/doc:~1~1org.cocoapods.SocialRadio~1documentation~1SocialRadio~1AutomixIQStatus~1playlistDiff\/fragments","op":"replace","value":[{"kind":"identifier","text":"playlistDiff"}]},{"path":"\/references\/doc:~1~1org.cocoapods.SocialRadio~1documentation~1SocialRadio~1AutomixIQStatus~1playlist\/title","op":"replace","value":"playlist"},{"path":"\/references\/doc:~1~1org.cocoapods.SocialRadio~1documentation~1SocialRadio~1AutomixIQStatus~1playlist\/fragments","op":"replace","value":[{"kind":"identifier","text":"playlist"}]},{"path":"\/references\/doc:~1~1org.cocoapods.SocialRadio~1documentation~1SocialRadio~1AutomixIQStatus~1playingTrackIdentifier\/title","op":"replace","value":"playingTrackIdentifier"},{"path":"\/references\/doc:~1~1org.cocoapods.SocialRadio~1documentation~1SocialRadio~1AutomixIQStatus~1playingTrackIdentifier\/fragments","op":"replace","value":[{"text":"playingTrackIdentifier","kind":"identifier"}]},{"path":"\/references\/doc:~1~1org.cocoapods.SocialRadio~1documentation~1SocialRadio~1AutomixIQPlaylistOperationType\/title","op":"replace","value":"AutomixIQPlaylistOperationType"},{"path":"\/references\/doc:~1~1org.cocoapods.SocialRadio~1documentation~1SocialRadio~1AutomixIQPlaylistOperationType\/fragments","op":"replace","value":[{"text":"AutomixIQPlaylistOperationType","kind":"identifier"}]},{"path":"\/references\/doc:~1~1org.cocoapods.SocialRadio~1documentation~1SocialRadio~1AutomixIQPlaylistOperationType\/navigatorTitle","op":"replace","value":[{"text":"AutomixIQPlaylistOperationType","kind":"identifier"}]},{"path":"\/references\/doc:~1~1org.cocoapods.SocialRadio~1documentation~1SocialRadio~1AutomixIQStatus~1muted\/title","op":"replace","value":"muted"},{"path":"\/references\/doc:~1~1org.cocoapods.SocialRadio~1documentation~1SocialRadio~1AutomixIQStatus~1muted\/fragments","op":"replace","value":[{"text":"muted","kind":"identifier"}]},{"path":"\/references\/doc:~1~1org.cocoapods.SocialRadio~1documentation~1SocialRadio~1AutomixIQStatus~1vinylStartStop\/title","op":"replace","value":"vinylStartStop"},{"path":"\/references\/doc:~1~1org.cocoapods.SocialRadio~1documentation~1SocialRadio~1AutomixIQStatus~1vinylStartStop\/fragments","op":"replace","value":[{"text":"vinylStartStop","kind":"identifier"}]},{"path":"\/references\/doc:~1~1org.cocoapods.SocialRadio~1documentation~1SocialRadio~1AutomixIQStatus~1canSkipToNext\/title","op":"replace","value":"canSkipToNext"},{"path":"\/references\/doc:~1~1org.cocoapods.SocialRadio~1documentation~1SocialRadio~1AutomixIQStatus~1canSkipToNext\/fragments","op":"replace","value":[{"text":"canSkipToNext","kind":"identifier"}]},{"path":"\/references\/doc:~1~1org.cocoapods.SocialRadio~1documentation~1SocialRadio~1AutomixIQStatus~1canOnOff\/title","op":"replace","value":"canOnOff"},{"path":"\/references\/doc:~1~1org.cocoapods.SocialRadio~1documentation~1SocialRadio~1AutomixIQStatus~1canOnOff\/fragments","op":"replace","value":[{"text":"canOnOff","kind":"identifier"}]},{"path":"\/references\/doc:~1~1org.cocoapods.SocialRadio~1documentation~1SocialRadio~1AutomixIQStatus~1playingTrackTotalTime\/title","op":"replace","value":"playingTrackTotalTime"},{"path":"\/references\/doc:~1~1org.cocoapods.SocialRadio~1documentation~1SocialRadio~1AutomixIQStatus~1playingTrackTotalTime\/fragments","op":"replace","value":[{"text":"playingTrackTotalTime","kind":"identifier"}]},{"path":"\/references\/doc:~1~1org.cocoapods.SocialRadio~1documentation~1SocialRadio~1AutomixIQStatus~1canReorderTracks\/title","op":"replace","value":"canReorderTracks"},{"path":"\/references\/doc:~1~1org.cocoapods.SocialRadio~1documentation~1SocialRadio~1AutomixIQStatus~1canReorderTracks\/fragments","op":"replace","value":[{"text":"canReorderTracks","kind":"identifier"}]},{"path":"\/references\/doc:~1~1org.cocoapods.SocialRadio~1documentation~1SocialRadio~1AutomixIQStatus~1failedTrackLoadIdentifiers\/title","op":"replace","value":"failedTrackLoadIdentifiers"},{"path":"\/references\/doc:~1~1org.cocoapods.SocialRadio~1documentation~1SocialRadio~1AutomixIQStatus~1failedTrackLoadIdentifiers\/fragments","op":"replace","value":[{"kind":"identifier","text":"failedTrackLoadIdentifiers"}]},{"path":"\/references\/doc:~1~1org.cocoapods.SocialRadio~1documentation~1SocialRadio~1AutomixIQStatus~1playing\/title","op":"replace","value":"playing"},{"path":"\/references\/doc:~1~1org.cocoapods.SocialRadio~1documentation~1SocialRadio~1AutomixIQStatus~1playing\/fragments","op":"replace","value":[{"text":"playing","kind":"identifier"}]},{"path":"\/references\/doc:~1~1org.cocoapods.SocialRadio~1documentation~1SocialRadio~1TunedRestDelegate\/title","op":"replace","value":"TunedRestDelegate"},{"path":"\/references\/doc:~1~1org.cocoapods.SocialRadio~1documentation~1SocialRadio~1TunedRestDelegate\/fragments","op":"replace","value":[{"text":"TunedRestDelegate","kind":"identifier"}]},{"path":"\/references\/doc:~1~1org.cocoapods.SocialRadio~1documentation~1SocialRadio~1TunedRestDelegate\/navigatorTitle","op":"replace","value":[{"text":"TunedRestDelegate","kind":"identifier"}]},{"path":"\/references\/doc:~1~1org.cocoapods.SocialRadio~1documentation~1SocialRadio~1AutomixIQWaveformModel\/title","op":"replace","value":"AutomixIQWaveformModel"},{"path":"\/references\/doc:~1~1org.cocoapods.SocialRadio~1documentation~1SocialRadio~1AutomixIQWaveformModel\/fragments","op":"replace","value":[{"text":"AutomixIQWaveformModel","kind":"identifier"}]},{"path":"\/references\/doc:~1~1org.cocoapods.SocialRadio~1documentation~1SocialRadio~1AutomixIQWaveformModel\/navigatorTitle","op":"replace","value":[{"text":"AutomixIQWaveformModel","kind":"identifier"}]},{"path":"\/references\/doc:~1~1org.cocoapods.SocialRadio~1documentation~1SocialRadio~1AutomixIQStatus~1explicitLyricsFiltering\/title","op":"replace","value":"explicitLyricsFiltering"},{"path":"\/references\/doc:~1~1org.cocoapods.SocialRadio~1documentation~1SocialRadio~1AutomixIQStatus~1explicitLyricsFiltering\/fragments","op":"replace","value":[{"kind":"identifier","text":"explicitLyricsFiltering"}]}],"traits":[{"interfaceLanguage":"occ"}]}]}